{"stationList":[{"beginRow":null,"endRow":null,"curPage":null,"pageRow":null,"totalCount":1,"rowNum":1,"selectedCount":1,"statnId":"1004000446","statnNm":"대야미","subwayId":"1004","subwayNm":"4호선","statnNmEng":"Daeyami Station","statnFid":"1004000445","statnFnm":"수리산","statnTid":"1004000447","statnTnm":"반월","operPblinstt":"서울메트로","zipNo":"426050","adresBass":"경기도 안산시 상록구 대야미동","adresDetail":"233-4","telno":"031-437-7788","fxnum":" ","directAt":"0","ord":null,"subwayXcnts":"192658.69131","subwayYcnts":"425467.7993","trnsitCo":"1","subwayList":"1004:1004000446,","pltfomSe":null,"gffDoor":null,"crosngAt":null,"toiletAt":null,"dspsnCvntlAt":null,"trttprkAt":null,"bcyclCstdyAt":null,"sctnTime":null,"sctnDstnc":null,"statnSn":null,"updnLine":null,"trainSttus":null,"lstcarAt":null,"imageX":null,"imageY":null,"trainNo":null,"lastRecptnDt":null}],"errorMessage":{"status":200,"code":"INFO-000","message":"정상 처리되었습니다.","link":"","developerMessage":"","total":1}}