{"stationList":[{"beginRow":null,"endRow":null,"curPage":null,"pageRow":null,"totalCount":1,"rowNum":1,"selectedCount":1,"statnId":"1009000904","statnNm":"신방화","subwayId":"1009","subwayNm":"9호선","statnNmEng":"Sinbanghwa","statnFid":"1009000903","statnFnm":"공항시장","statnTid":"1009000905","statnTnm":"마곡나루","operPblinstt":"메트로9","zipNo":"157220","adresBass":"서울특별시 강서구 방화동","adresDetail":"17-156","telno":"02-2656-0904","fxnum":" ","directAt":"0","ord":null,"subwayXcnts":"183819.28777","subwayYcnts":"452029.73979","trnsitCo":"1","subwayList":"1009:1009000904,","pltfomSe":null,"gffDoor":null,"crosngAt":null,"toiletAt":null,"dspsnCvntlAt":null,"trttprkAt":null,"bcyclCstdyAt":null,"sctnTime":null,"sctnDstnc":null,"statnSn":null,"updnLine":null,"trainSttus":null,"lstcarAt":null,"imageX":null,"imageY":null,"trainNo":null,"lastRecptnDt":null}],"errorMessage":{"status":200,"code":"INFO-000","message":"정상 처리되었습니다.","link":"","developerMessage":"","total":1}}