{"stationList":[{"beginRow":null,"endRow":null,"curPage":null,"pageRow":null,"totalCount":2,"rowNum":1,"selectedCount":2,"statnId":"1003000330","statnNm":"을지로3가","subwayId":"1003","subwayNm":"3호선","statnNmEng":"Euljiro 3(sam)-ga","statnFid":"1003000329","statnFnm":"종로3가","statnTid":"1003000331","statnTnm":"충무로","operPblinstt":"서울메트로","zipNo":"100193","adresBass":"서울특별시 중구 을지로3가","adresDetail":"70-1","telno":"02-6110-2031","fxnum":" ","directAt":"0","ord":null,"subwayXcnts":"199351.74858","subwayYcnts":"451872.9288","trnsitCo":"2","subwayList":"1002:1002000203,1003:1003000330,","pltfomSe":null,"gffDoor":null,"crosngAt":null,"toiletAt":null,"dspsnCvntlAt":null,"trttprkAt":null,"bcyclCstdyAt":null,"sctnTime":null,"sctnDstnc":null,"statnSn":null,"updnLine":null,"trainSttus":null,"lstcarAt":null,"imageX":null,"imageY":null,"trainNo":null,"lastRecptnDt":null},{"beginRow":null,"endRow":null,"curPage":null,"pageRow":null,"totalCount":2,"rowNum":2,"selectedCount":2,"statnId":"1002000203","statnNm":"을지로3가","subwayId":"1002","subwayNm":"2호선","statnNmEng":"Euljiro 3(sam)-ga","statnFid":"1002000202","statnFnm":"을지로입구","statnTid":"1002000204","statnTnm":"을지로4가","operPblinstt":"서울메트로","zipNo":"100193","adresBass":"서울특별시 중구 을지로3가","adresDetail":"70-1","telno":"02-6110-3301","fxnum":" ","directAt":"0","ord":null,"subwayXcnts":"199176.7","subwayYcnts":"451859.5","trnsitCo":"2","subwayList":"1002:1002000203,1003:1003000330,","pltfomSe":null,"gffDoor":null,"crosngAt":null,"toiletAt":null,"dspsnCvntlAt":null,"trttprkAt":null,"bcyclCstdyAt":null,"sctnTime":null,"sctnDstnc":null,"statnSn":null,"updnLine":null,"trainSttus":null,"lstcarAt":null,"imageX":null,"imageY":null,"trainNo":null,"lastRecptnDt":null}],"errorMessage":{"status":200,"code":"INFO-000","message":"정상 처리되었습니다.","link":"","developerMessage":"","total":2}}